kernel_catalogo_videos/__init__.py
kernel_catalogo_videos/castmembers/__init__.py
kernel_catalogo_videos/castmembers/application/__init__.py
kernel_catalogo_videos/castmembers/application/use_cases/__init__.py
kernel_catalogo_videos/castmembers/application/use_cases/create/__init__.py
kernel_catalogo_videos/castmembers/application/use_cases/create/create.http
kernel_catalogo_videos/castmembers/application/use_cases/create/create.uml
kernel_catalogo_videos/castmembers/application/use_cases/create/input.py
kernel_catalogo_videos/castmembers/application/use_cases/create/output.py
kernel_catalogo_videos/castmembers/application/use_cases/create/use_case.py
kernel_catalogo_videos/castmembers/application/use_cases/delete/__init__.py
kernel_catalogo_videos/castmembers/application/use_cases/delete/delete.http
kernel_catalogo_videos/castmembers/application/use_cases/delete/delete.puml
kernel_catalogo_videos/castmembers/application/use_cases/delete/input.py
kernel_catalogo_videos/castmembers/application/use_cases/delete/use_case.py
kernel_catalogo_videos/castmembers/application/use_cases/dto.py
kernel_catalogo_videos/castmembers/application/use_cases/get/__init__.py
kernel_catalogo_videos/castmembers/application/use_cases/get/get.http
kernel_catalogo_videos/castmembers/application/use_cases/get/input.py
kernel_catalogo_videos/castmembers/application/use_cases/get/output.py
kernel_catalogo_videos/castmembers/application/use_cases/get/use_case.py
kernel_catalogo_videos/castmembers/application/use_cases/search/__init__.py
kernel_catalogo_videos/castmembers/application/use_cases/search/input.py
kernel_catalogo_videos/castmembers/application/use_cases/search/output.py
kernel_catalogo_videos/castmembers/application/use_cases/search/search.http
kernel_catalogo_videos/castmembers/application/use_cases/search/use_case.py
kernel_catalogo_videos/castmembers/application/use_cases/update/__init__.py
kernel_catalogo_videos/castmembers/application/use_cases/update/input.py
kernel_catalogo_videos-0.1.10.dist-info/WHEEL
kernel_catalogo_videos-0.1.10.dist-info/METADATA
kernel_catalogo_videos-0.1.10.dist-info/RECORD
