Metadata-Version: 2.1
Name: kernel-catalogo-videos
Version: 0.1.10
Summary: 
Author: Lucas
Author-email: lucassrod@gmail.com
Requires-Python: >=3.10,<4.0
Classifier: Programming Language :: Python :: 3
Classifier: Programming Language :: Python :: 3.10
Requires-Dist: pika (>=1.3.1,<2.0.0)
Requires-Dist: python-slugify (>=7.0.0,<8.0.0)
Requires-Dist: structlog (>=22.3.0,<23.0.0)
